spotter/__init__.py
spotter/__main__.py
spotter/spotter.py
spotter/watches.py
spotter-1.7.1.dist-info/DESCRIPTION.rst
spotter-1.7.1.dist-info/METADATA
spotter-1.7.1.dist-info/RECORD
spotter-1.7.1.dist-info/WHEEL
spotter-1.7.1.dist-info/entry_points.txt
spotter-1.7.1.dist-info/metadata.json
spotter-1.7.1.dist-info/top_level.txt
