Metadata-Version: 2.0
Name: spotter
Version: 1.7.1
Summary: A command line tool for watching files and running shell commands when they change.
Home-page: http://github.com/borntyping/spotter
Author: Sam Clements
Author-email: sam@borntyping.co.uk
License: MIT
Platform: UNKNOWN
Classifier: Development Status :: 5 - Production/Stable
Classifier: Environment :: Console
Classifier: License :: OSI Approved :: MIT License
Classifier: Operating System :: OS Independent
Classifier: Operating System :: Unix
Classifier: Programming Language :: Python :: 2
Classifier: Programming Language :: Python :: 2.7
Classifier: Programming Language :: Python :: 3
Classifier: Programming Language :: Python :: 3.2
Classifier: Topic :: Software Development :: Testing
Classifier: Topic :: System :: Monitoring
Classifier: Topic :: Utilities
Requires-Dist: pyinotify (>=0.9.4)
